papersize/__init__.py
papersize/py.typed
papersize/papersize.egg-info/PKG-INFO
papersize/papersize.egg-info/SOURCES.txt
papersize/papersize.egg-info/dependency_links.txt
papersize/papersize.egg-info/not-zip-safe
papersize/papersize.egg-info/top_level.txt
papersize/translations/.gitignore
papersize/translations/fr/LC_MESSAGES/papersize.mo
papersize/translations/fr/LC_MESSAGES/papersize.po
papersize-1.7.0.dist-info/METADATA
papersize-1.7.0.dist-info/WHEEL
papersize-1.7.0.dist-info/licenses/AUTHORS
papersize-1.7.0.dist-info/licenses/LICENSE
papersize-1.7.0.dist-info/RECORD
