Metadata-Version: 2.4
Name: papersize
Version: 1.7.0
Summary: Paper size related tools
Project-URL: Homepage, http://framagit.org/spalax/papersize
Project-URL: Issues, https://framagit.org/spalax/papersize/issues
Project-URL: Documentation, http://papersize.readthedocs.io
Author-email: Louis Paternault <spalax@gresille.org>
License-File: AUTHORS
License-File: LICENSE
Keywords: paper,size,standard
Classifier: Development Status :: 5 - Production/Stable
Classifier: Intended Audience :: Developers
Classifier: License :: OSI Approved :: GNU General Public License v3 or later (GPLv3+)
Classifier: Operating System :: OS Independent
Classifier: Programming Language :: Python
Classifier: Programming Language :: Python :: 3
Classifier: Programming Language :: Python :: 3.12
Classifier: Programming Language :: Python :: 3.13
Classifier: Programming Language :: Python :: 3.14
Classifier: Programming Language :: Python :: 3.15
Classifier: Topic :: Printing
Requires-Python: <4,>=3.12
